jsonrpc2pyclient/__init__.py
jsonrpc2pyclient/_irpcclient.py
jsonrpc2pyclient/decorator.py
jsonrpc2pyclient/httpclient.py
jsonrpc2pyclient/rpcclient.py
jsonrpc2pyclient/wsclient.py
jsonrpc2_pyclient-5.2.0.dist-info/LICENSE
jsonrpc2_pyclient-5.2.0.dist-info/WHEEL
jsonrpc2_pyclient-5.2.0.dist-info/METADATA
jsonrpc2_pyclient-5.2.0.dist-info/RECORD
