Metadata-Version: 2.1
Name: jsonrpc2-pyclient
Version: 5.2.0
Summary: Python JSON-RPC 2.0 client library.
Home-page: https://gitlab.com/mburkard/jsonrpc2-pyclient
License: AGPL-3.0-or-later
Author: Matthew Burkard
Author-email: matthewjburkard@gmail.com
Requires-Python: >=3.9,<4.0
Classifier: License :: OSI Approved :: GNU Affero General Public License v3 or later (AGPLv3+)
Classifier: Programming Language :: Python :: 3
Classifier: Programming Language :: Python :: 3.10
Classifier: Programming Language :: Python :: 3.9
Requires-Dist: httpx (>=0.26.0,<0.27.0)
Requires-Dist: jsonrpc2-objects (>=4.0.0,<5.0.0)
Requires-Dist: py-undefined (>=0.1.7,<0.2.0)
Requires-Dist: websockets (>=12.0,<13.0)
Project-URL: Repository, https://gitlab.com/mburkard/jsonrpc2-pyclient
